{"title":"An Example Diagram","elements":{"anchors":{"848":{"id":848,"x":400,"y":300},"6554":{"id":6554,"x":250,"y":300},"7226":{"id":7226,"x":500,"y":200},"7278":{"id":7278,"x":500,"y":400},"7488":{"id":7488,"x":150,"y":200},"7903":{"id":7903,"x":150,"y":400}},"propagators":{"375":{"id":375,"kind":"fermion","anchor1":848,"anchor2":7226,"arrow":0},"2046":{"id":2046,"kind":"fermion","anchor1":6554,"anchor2":848,"arrow":0},"3480":{"id":3480,"kind":"fermion","anchor1":7488,"anchor2":6554,"arrow":0},"4686":{"id":4686,"kind":"fermion","anchor1":848,"anchor2":7278,"arrow":0},"6252":{"id":6252,"kind":"fermion","anchor1":7903,"anchor2":6554,"arrow":0}},"text":{},"shapes":{}}}